t5chem/__init__.py
t5chem/__main__.py
t5chem/__version__.py
t5chem/data_utils.py
t5chem/evaluation.py
t5chem/model.py
t5chem/mol_tokenizers.py
t5chem/run_prediction.py
t5chem/run_trainer.py
t5chem/archived/MultiTask.py
t5chem/preprocessing/parse_USPTO.py
t5chem/preprocessing/preprocess_utils.py
t5chem/vocab/atom.txt
t5chem/vocab/selfies.txt
t5chem/vocab/simple.txt
t5chem-1.2.0.dist-info/LICENSE
t5chem-1.2.0.dist-info/METADATA
t5chem-1.2.0.dist-info/WHEEL
t5chem-1.2.0.dist-info/entry_points.txt
t5chem-1.2.0.dist-info/top_level.txt
t5chem-1.2.0.dist-info/RECORD
