Metadata-Version: 2.1
Name: t5chem
Version: 1.2.0
Summary: A Unified Deep Learning Model for Multi-task Reaction Predictions
Author-email: Jocelyn Lu <jl8570@nyu.edu>
License: MIT
Project-URL: Homepage, https://github.com/HelloJocelynLu/t5chem
Classifier: Development Status :: 2 - Pre-Alpha
Classifier: License :: OSI Approved :: MIT License
Classifier: Programming Language :: Python :: 3.7
Requires-Python: >=3.7
License-File: LICENSE
Requires-Dist: transformers>=4.38.0
Requires-Dist: accelerate>=0.26.0
Requires-Dist: tokenizers>=0.19.1
Requires-Dist: torch>=2.2.0
Requires-Dist: scikit-learn>=1.5.0
Requires-Dist: scipy>=1.6.0
Requires-Dist: wandb>=0.18.0
Requires-Dist: pandas>=1.2.4
Requires-Dist: rdkit>=2022.9.4
